<?xml version="1.0" encoding="UTF-8" standalone="no"?>
<manifest xmlns="http://tizen.org/ns/packages" api-version="4.0" package="org.example.basicui3" version="1.0.0">
    <profile name="wearable"/>
    <ui-application appid="org.example.basicui3" exec="basicui3" multiple="false" nodisplay="false" taskmanage="true" type="capp">
        <label>basicui3</label>
        <icon>basicui3.png</icon>
    </ui-application>
    <privileges>
        <privilege>http://tizen.org/privilege/mediastorage</privilege>
        <privilege>http://tizen.org/privilege/appmanager.launch</privilege>
        <privilege>http://tizen.org/privilege/externalstorage.appdata</privilege>
    </privileges>
</manifest>
